{
  "devsData": [
    {
      "name": "MD ACHEM KHAN",
      "uName": "mdachem6",
      "email": "mdachem6@gmail.com",
      "phone": "01764849199",
      "gender": "",
      "skill": "MERN",
      "image": "https://i.ibb.co/G5yyssZ/Scuare.jpg",
      "facebook": "https://www.facebook.com/achem.6/",
      "twitter": "#",
      "instagram": "#",
      "linkedin": "#",
      "github": "#",
      "youtube": "#",
      "status": true,
      "id": 1
    },
    {
      "name": "Rupa Roy",
      "uName": "ruparoy",
      "email": "rupa@gmail.com",
      "phone": "017123456789",
      "gender": "Female",
      "skill": "Java Scripts",
      "image": "https://i.ibb.co/x265prh/Rupa-Roy.jpg",
      "facebook": "#",
      "twitter": "",
      "instagram": "#",
      "linkedin": "",
      "github": "",
      "youtube": "",
      "status": false,
      "id": 2
    },
    {
      "name": "MD ADNAN",
      "uName": "adnan74",
      "email": "adnan@gmail.com",
      "phone": "017645899563",
      "gender": "Male",
      "skill": "PHP",
      "image": "https://i.ibb.co/MknNBJ5/Adnan.jpg",
      "facebook": "#",
      "twitter": "#",
      "instagram": "#",
      "linkedin": "#",
      "github": "",
      "youtube": "#",
      "status": true,
      "id": 3
    },
    {
      "name": "MD NAHID",
      "uName": "nahid",
      "email": "nahid@gmail.com",
      "phone": "01788956635",
      "gender": "Male",
      "skill": "Facebook Marketor",
      "image": "https://i.ibb.co/C9sC90b/MD-Nahid.jpg",
      "facebook": "#",
      "twitter": "#",
      "instagram": "",
      "linkedin": "#",
      "github": "",
      "youtube": "",
      "status": false,
      "id": 4
    },
    {
      "name": "Abu Raihan",
      "uName": "aburaihan",
      "email": "raihan@gmail.com",
      "phone": "01766985563`",
      "gender": "Male",
      "skill": "Laravel",
      "image": "https://i.ibb.co/QFfbxkt/MD-Abu-Rayhan.jpg",
      "facebook": "#",
      "twitter": "#",
      "instagram": "#",
      "linkedin": "#",
      "github": "#",
      "youtube": "",
      "status": true,
      "id": 5
    },
    {
      "name": "MD Akash",
      "uName": "mdakash",
      "email": "akash@gmail.com",
      "phone": "015889686635",
      "gender": "Male",
      "skill": "Java Scripts",
      "image": "https://i.ibb.co/Mcpx4y1/0c6c073671d34e79d9e37580578ee239.jpg",
      "facebook": "#",
      "twitter": "#",
      "instagram": "",
      "linkedin": "",
      "github": "#",
      "youtube": "",
      "id": 10,
      "status": true
    },
    {
      "name": "Sharmin Begum",
      "uName": "sharmin",
      "email": "sharmin@gmail.com",
      "phone": "016558996336",
      "gender": "Female",
      "skill": "PHP",
      "image": "https://i.ibb.co/zNqKYjC/fc4cd1e04c2cd58f8de7602ef24ae475-karibu-korean-art.jpg",
      "facebook": "#",
      "twitter": "#",
      "instagram": "",
      "linkedin": "",
      "github": "#",
      "youtube": "",
      "status": true,
      "id": 11
    },
    {
      "name": "Developer Achem",
      "uName": "developerachem",
      "email": "developerachem@gmail.com",
      "phone": "01754774203",
      "gender": "Male",
      "skill": "Full Stack Developer",
      "image": "https://i.ibb.co/6ZQ01rM/Achem.jpg",
      "facebook": "#",
      "twitter": "#",
      "instagram": "#",
      "linkedin": "#",
      "github": "#",
      "youtube": "#",
      "id": 12,
      "status": true
    },
    {
      "name": "Abu Sayeed",
      "uName": "abu sayeed",
      "email": "abusayeed@gmail.com",
      "phone": "+668569645",
      "gender": "Male",
      "skill": "Java Scripts",
      "image": "https://i.ibb.co/gJGjyGL/MD-Abu-Sayeed.jpg",
      "facebook": "#",
      "twitter": "#",
      "instagram": "#",
      "linkedin": "#",
      "github": "",
      "youtube": "",
      "status": true,
      "id": 13
    }
  ]
}